notifer_cli/__init__.py
notifer_cli/cli.py
notifer_cli/client.py
notifer_cli/config.py
notifer_cli/commands/__init__.py
notifer_cli/commands/auth.py
notifer_cli/commands/config.py
notifer_cli/commands/keys.py
notifer_cli/commands/publish.py
notifer_cli/commands/subscribe.py
notifer_cli/commands/topics.py
notifer_cli-1.0.1.dist-info/licenses/LICENSE
notifer_cli-1.0.1.dist-info/METADATA
notifer_cli-1.0.1.dist-info/WHEEL
notifer_cli-1.0.1.dist-info/entry_points.txt
notifer_cli-1.0.1.dist-info/top_level.txt
notifer_cli-1.0.1.dist-info/RECORD
