Metadata-Version: 2.4
Name: notifer-cli
Version: 1.0.1
Summary: Command-line interface for Notifer notification service
Author-email: Notifer Team <hello@notifer.io>
License: MIT
Project-URL: Homepage, https://notifer.io
Project-URL: Documentation, https://docs.notifer.io
Project-URL: Repository, https://github.com/nexolab-projects/notifer-cli
Project-URL: Issues, https://github.com/nexolab-projects/notifer-cli/issues
Keywords: notifications,cli,pub-sub,push-notifications
Classifier: Development Status :: 4 - Beta
Classifier: Environment :: Console
Classifier: Intended Audience :: Developers
Classifier: Topic :: Communications
Classifier: Topic :: Utilities
Classifier: License :: OSI Approved :: MIT License
Classifier: Operating System :: OS Independent
Classifier: Programming Language :: Python :: 3
Classifier: Programming Language :: Python :: 3.11
Classifier: Programming Language :: Python :: 3.12
Classifier: Programming Language :: Python :: 3.13
Requires-Python: >=3.11
License-File: LICENSE
Requires-Dist: click>=8.1.0
Requires-Dist: requests>=2.31.0
Requires-Dist: pyyaml>=6.0
Requires-Dist: rich>=13.0.0
Requires-Dist: sseclient-py>=1.8.0
Dynamic: license-file
